mltins/__init__.py
mltins/pagerank.py
mltins-0.0.1.dist-info/LICENSE
mltins-0.0.1.dist-info/METADATA
mltins-0.0.1.dist-info/WHEEL
mltins-0.0.1.dist-info/top_level.txt
mltins-0.0.1.dist-info/RECORD
