Metadata-Version: 2.1
Name: mltins
Version: 0.0.1
Summary: A project for matching learing.
Home-page: https://github.com/onwardever/mltins.git
Author: yangdian
Author-email: 2406616734@qq.com
Keywords: ml
Requires-Python: >=3.6, <4
License-File: LICENSE
